pdf2table/__init__.py
pdf2table/driver.py
pdf2table/document/__init__.py
pdf2table/document/image.py
pdf2table/document/page.py
pdf2table/document/pdf.py
pdf2table/table/__init__.py
pdf2table/table/metrics.py
pdf2table/table/utils.py
pdf2table/table/processing/__init__.py
pdf2table/table/processing/common.py
pdf2table/table/processing/bordered_tables/__init__.py
pdf2table/table/processing/bordered_tables/line.py
pdf2table/table/processing/bordered_tables/cells/__init__.py
pdf2table/table/processing/bordered_tables/cells/deduplication.py
pdf2table/table/processing/bordered_tables/cells/identification.py
pdf2table/table/processing/bordered_tables/tables/__init__.py
pdf2table/table/processing/bordered_tables/tables/cell_clustering.py
pdf2table/table/processing/bordered_tables/tables/implicit_rows.py
pdf2table/table/processing/bordered_tables/tables/semi_bordered.py
pdf2table/table/processing/bordered_tables/tables/table_creation.py
pdf2table/table/processing/borderless_tables/__init__.py
pdf2table/table/processing/borderless_tables/columns.py
pdf2table/table/processing/borderless_tables/model.py
pdf2table/table/processing/borderless_tables/rows.py
pdf2table/table/processing/borderless_tables/whitespaces.py
pdf2table/table/processing/borderless_tables/layout/__init__.py
pdf2table/table/processing/borderless_tables/layout/column_segments.py
pdf2table/table/processing/borderless_tables/layout/image_elements.py
pdf2table/table/processing/borderless_tables/layout/rlsa.py
pdf2table/table/processing/borderless_tables/layout/table_segments.py
pdf2table/table/processing/borderless_tables/table/__init__.py
pdf2table/table/processing/borderless_tables/table/coherency.py
pdf2table/table/processing/borderless_tables/table/table_creation.py
pdf2table/table/structure/__init__.py
pdf2table/table/structure/models.py
pdf2table/table/structure/table_object.py
pdf2table/tatr/__init__.py
pdf2table-0.1.4.dist-info/LICENSE
pdf2table-0.1.4.dist-info/METADATA
pdf2table-0.1.4.dist-info/WHEEL
pdf2table-0.1.4.dist-info/top_level.txt
pdf2table-0.1.4.dist-info/RECORD
