Metadata-Version: 2.1
Name: pdf2table
Version: 0.1.4
Summary: pdf2table is a powerful Python tool designed to streamline the extraction of tabular data from PDF documents.
Home-page: https://github.com/li-rongzhi/pdf2table
Author: rngzhi
License: MIT
Classifier: Programming Language :: Python :: 3
Classifier: License :: OSI Approved :: MIT License
Classifier: Operating System :: OS Independent
License-File: LICENSE
Requires-Dist: polars
Requires-Dist: opencv-contrib-python
Requires-Dist: numba
Requires-Dist: numpy
Requires-Dist: easyocr
Requires-Dist: pdf2image
Requires-Dist: torch
Requires-Dist: transformers
Requires-Dist: pandas
Requires-Dist: pypdf
Requires-Dist: poppler-utils
